LICENSE.txt
MANIFEST.in
README.rst
setup.cfg
setup.py
navi/.DS_Store
navi/__init__.py
navi/commands.py
navi/context.py
navi/core.py
navi/handlers.py
navi/intents.py
navi/register.py
navi.egg-info/PKG-INFO
navi.egg-info/SOURCES.txt
navi.egg-info/dependency_links.txt
navi.egg-info/entry_points.txt
navi.egg-info/not-zip-safe
navi.egg-info/requires.txt
navi.egg-info/top_level.txt
navi/conversational/__init__.py
navi/conversational/wit_ai.py
navi/messaging/__init__.py
navi/messaging/telegram_platform.py
navi/navi.egg-info/PKG-INFO
navi/navi.egg-info/SOURCES.txt
navi/navi.egg-info/dependency_links.txt
navi/navi.egg-info/not-zip-safe
navi/navi.egg-info/requires.txt
navi/navi.egg-info/top_level.txt
navi/resources/.DS_Store
navi/resources/logo/navi_framework_v1_thin.png
navi/resources/sounds/ding.wav
navi/resources/sounds/dong.wav
navi/speech/.DS_Store
navi/speech/__init__.py
navi/speech/hotword.py
navi/speech/recognition.py
navi/speech/snowboywrapper.py
navi/speech/sounds.py
navi/templates/config.py.tpl
navi/templates/handlers.py.tpl
navi/templates/intents.py.tpl
navi/templates/interfaces.py.tpl
navi/templates/run.py.tpl
navi/templates/secret_config.py.tpl