Metadata-Version: 1.0
Name: navi
Version: 0.1.0a17
Summary: A framework for quickly building better and open personal assistants
Home-page: https://github.com/leosampaio/navi-framework
Author: Leonardo Sampaio Ferraz Ribeiro
Author-email: leo.sampaio.ferraz.ribeiro@gmail.com
License: BSD
Keywords: navi assistant bot chatbot framework
Platform: UNKNOWN
